odoo/addons/sale_order_line_chained_move/README.rst
odoo/addons/sale_order_line_chained_move/__init__.py
odoo/addons/sale_order_line_chained_move/__manifest__.py
odoo/addons/sale_order_line_chained_move/hooks.py
odoo/addons/sale_order_line_chained_move/demo/sale_order.xml
odoo/addons/sale_order_line_chained_move/i18n/sale_order_line_chained_move.pot
odoo/addons/sale_order_line_chained_move/models/__init__.py
odoo/addons/sale_order_line_chained_move/models/sale_order_line.py
odoo/addons/sale_order_line_chained_move/models/stock_move.py
odoo/addons/sale_order_line_chained_move/models/stock_rule.py
odoo/addons/sale_order_line_chained_move/readme/CONTRIBUTORS.rst
odoo/addons/sale_order_line_chained_move/readme/DESCRIPTION.rst
odoo/addons/sale_order_line_chained_move/static/description/icon.png
odoo/addons/sale_order_line_chained_move/static/description/index.html
odoo/addons/sale_order_line_chained_move/tests/__init__.py
odoo/addons/sale_order_line_chained_move/tests/test_chained_move.py
odoo13_addon_sale_order_line_chained_move-13.0.1.0.1.dist-info/METADATA
odoo13_addon_sale_order_line_chained_move-13.0.1.0.1.dist-info/WHEEL
odoo13_addon_sale_order_line_chained_move-13.0.1.0.1.dist-info/top_level.txt
odoo13_addon_sale_order_line_chained_move-13.0.1.0.1.dist-info/RECORD
